odoo/addons/shopinvader_invoice_payment/README.rst
odoo/addons/shopinvader_invoice_payment/__init__.py
odoo/addons/shopinvader_invoice_payment/__manifest__.py
odoo/addons/shopinvader_invoice_payment/components/__init__.py
odoo/addons/shopinvader_invoice_payment/components/payment_transaction_event_listerner.py
odoo/addons/shopinvader_invoice_payment/i18n/shopinvader_invoice_payment.pot
odoo/addons/shopinvader_invoice_payment/models/__init__.py
odoo/addons/shopinvader_invoice_payment/models/account_move.py
odoo/addons/shopinvader_invoice_payment/models/shopinvader_payment.py
odoo/addons/shopinvader_invoice_payment/readme/CONTRIBUTORS.rst
odoo/addons/shopinvader_invoice_payment/readme/DESCRIPTION.rst
odoo/addons/shopinvader_invoice_payment/services/__init__.py
odoo/addons/shopinvader_invoice_payment/services/invader_payment_service.py
odoo/addons/shopinvader_invoice_payment/services/invoice.py
odoo/addons/shopinvader_invoice_payment/static/description/index.html
odoo/addons/shopinvader_invoice_payment/tests/__init__.py
odoo/addons/shopinvader_invoice_payment/tests/test_shopinvader_invoice_payment.py
odoo14_addon_shopinvader_invoice_payment-14.0.1.0.3.dist-info/METADATA
odoo14_addon_shopinvader_invoice_payment-14.0.1.0.3.dist-info/WHEEL
odoo14_addon_shopinvader_invoice_payment-14.0.1.0.3.dist-info/top_level.txt
odoo14_addon_shopinvader_invoice_payment-14.0.1.0.3.dist-info/RECORD
