Metadata-Version: 2.1
Name: odoo14-addon-shopinvader-invoice-payment
Version: 14.0.1.0.3
Summary: Invoice payment integration for Shopinvader
Home-page: https://github.com/shopinvader/odoo-shopinvader-payment
Author: ACSONE SA/NV
License: AGPL-3
Platform: UNKNOWN
Classifier: Programming Language :: Python
Classifier: Framework :: Odoo
Classifier: Framework :: Odoo :: 14.0
Classifier: License :: OSI Approved :: GNU Affero General Public License v3
Requires-Python: >=3.6
Requires-Dist: cerberus
Requires-Dist: odoo14-addon-account-payment-partner
Requires-Dist: odoo14-addon-component-event
Requires-Dist: odoo14-addon-invader-invoice-payment
Requires-Dist: odoo14-addon-onchange-helper
Requires-Dist: odoo14-addon-shopinvader-invoice
Requires-Dist: odoo14-addon-shopinvader-payment
Requires-Dist: odoo (<14.1dev,>=14.0a)
Requires-Dist: unidecode
